setup.py
nva/__init__.py
nva/__init__.pyc
nva.stormcontainer.egg-info/PKG-INFO
nva.stormcontainer.egg-info/SOURCES.txt
nva.stormcontainer.egg-info/dependency_links.txt
nva.stormcontainer.egg-info/entry_points.txt
nva.stormcontainer.egg-info/namespace_packages.txt
nva.stormcontainer.egg-info/not-zip-safe
nva.stormcontainer.egg-info/requires.txt
nva.stormcontainer.egg-info/top_level.txt
nva/stormcontainer/README.txt
nva/stormcontainer/__init__.py
nva/stormcontainer/container.py
nva/stormcontainer/interfaces.py
nva/stormcontainer/utils.py
nva/stormcontainer/tests/__init__.py
nva/stormcontainer/tests/test_doctests.py
nva/stormcontainer/tests/test_unittests.py
