Metadata-Version: 1.0
Name: nva.stormcontainer
Version: 0.2
Summary: A Zope Storm Container
Home-page: http://www.novareto.de
Author: 'Christian Klinger'
Author-email: cklinger@novareto.de
License: GPL
Keywords: Storm Zope
Platform: UNKNOWN
Classifier: Framework :: Plone
Classifier: Framework :: Zope2
Classifier: Framework :: Zope3
Classifier: Programming Language :: Python
Classifier: Topic :: Software Development :: Libraries :: Python Modules
